datasciencefunctions/_MlModel.py
datasciencefunctions/__init__.py
datasciencefunctions/__version__.py
datasciencefunctions/_classification.py
datasciencefunctions/_data_exploration.py
datasciencefunctions/_data_processing.py
datasciencefunctions/_datasets.py
datasciencefunctions/_feature_selection.py
datasciencefunctions/_online_marketing.py
datasciencefunctions/_supervised.py
datasciencefunctions/_utils.py
datasciencefunctions/classification.py
datasciencefunctions/data_exploration.py
datasciencefunctions/data_processing.py
datasciencefunctions/feature_selection.py
datasciencefunctions/online_marketing.py
datasciencefunctions/supervised.py
datasciencefunctions/utils.py
datasciencefunctions-0.2.0.dist-info/LICENSE
datasciencefunctions-0.2.0.dist-info/METADATA
datasciencefunctions-0.2.0.dist-info/WHEEL
datasciencefunctions-0.2.0.dist-info/top_level.txt
datasciencefunctions-0.2.0.dist-info/RECORD
