Metadata-Version: 2.1
Name: datasciencefunctions
Version: 0.2.0
Summary: Data science utilities and code snippets for reuse.
Home-page: UNKNOWN
Author: DataSentics
License: UNKNOWN
Platform: UNKNOWN
Classifier: Programming Language :: Python :: 3
License-File: LICENSE
